EyesLibraryExtended/__init__.py
EyesLibraryExtended/version.py
EyesLibraryExtended/keywords/__init__.py
EyesLibraryExtended/keywords/check.py
EyesLibraryExtended/keywords/session.py
EyesLibraryExtended/keywords/target.py
EyesLibraryExtended/resources/__init__.py
EyesLibraryExtended/resources/utils.py
EyesLibraryExtended/resources/variables.py
robotframework_eyeslibraryextended-4.1.dist-info/LICENSE.txt
robotframework_eyeslibraryextended-4.1.dist-info/METADATA
robotframework_eyeslibraryextended-4.1.dist-info/WHEEL
robotframework_eyeslibraryextended-4.1.dist-info/top_level.txt
robotframework_eyeslibraryextended-4.1.dist-info/RECORD
